[
  
    {
      "title"    : "Článek s embeddnutým flickerem",
      "author"   : "Jmeno Prijmeni",
      "category" : "blog",
      "content"	 : "",
      "url"      : "/aktuality/clanek-s-embeddnutym-flickerem.html",
      "date"     : "2018-07-22 00:00:00 +0200"
    },
  
    {
      "title"    : "Článek s videem místo obrázku",
      "author"   : "Jmeno Prijmeni",
      "category" : "blog",
      "content"	 : "Posty musí být každý ve vlastním souboru pojmenovaném datumem a nejakym nazvem, například _posts/2018-03-14-slavime-pi-day.md. Tento název se pak objeví v adrese, tedy xxx.pirati.cz/aktuality/slavime-pi-day.html.Obrázky dávejte do assets/img/posts/Struktura  texty pište v Markdown  viz wikipediaUkázky typografieNadpis 1Nadpis 2Nadpis 3Nadpis 4Nullam lectus justo, vulputate eget mollis sed, tempor sed magna. Etiam commododui eget wisi. Cras elementum. Etiam dictum tincidunt diam. Aliquam eratvolutpat. Duis sapien nunc, commodo et, interdum suscipit, sollicitudin et,dolor. Aliquam erat volutpat. Etiam ligula pede, sagittis quis, interdumultricies, scelerisque eu. Cras elementum. Vestibulum fermentum tortor id mi.Etiam quis quam. Mauris elementum mauris vitae tortor. Fusce tellus. Integerrutrum, orci vestibulum ullamcorper ultricies, lacus quam ultricies odio, vitaeplacerat pede sem sit amet enim. Ut enim ad minima veniam, quis nostrumexercitationem ullam corporis suscipit laboriosam, nisi ut aliquid ex ea commodiconsequatur?Nadpis 1Nullam lectus justo, vulputate eget mollis sed, tempor sed magna. Etiam commododui eget wisi. Cras elementum. Etiam dictum tincidunt diam. Aliquam eratvolutpat. Duis sapien nunc, commodo et, interdum suscipit, sollicitudin et,dolor. Aliquam erat volutpat.Nadpis 2Nullam lectus justo, vulputate eget mollis sed, tempor sed magna. Etiam commododui eget wisi. Cras elementum. Etiam dictum tincidunt diam. Aliquam eratvolutpat. Duis sapien nunc, commodo et, interdum suscipit, sollicitudin et,dolor. Aliquam erat volutpat.Nadpis 3Nullam lectus justo, vulputate eget mollis sed, tempor sed magna. Etiam commododui eget wisi. Cras elementum. Etiam dictum tincidunt diam. Aliquam eratvolutpat. Duis sapien nunc, commodo et, interdum suscipit, sollicitudin et,dolor. Aliquam erat volutpat.Nadpis 4Nullam lectus justo, vulputate eget mollis sed, tempor sed magna. Etiam commododui eget wisi. Cras elementum. Etiam dictum tincidunt diam. Aliquam eratvolutpat. Duis sapien nunc, commodo et, interdum suscipit, sollicitudin et,dolor. Aliquam erat volutpat.Nečíslovaný seznam  Quisque porta. Nulla pulvinar eleifend sem.  Quisque porta. Nulla pulvinar eleifend sem.  Quisque porta. Nulla pulvinar eleifend sem.  Quisque porta. Nulla pulvinar eleifend sem.Číslovaný seznam  Quisque porta. Nulla pulvinar eleifend sem.  Quisque porta. Nulla pulvinar eleifend sem.  Quisque porta. Nulla pulvinar eleifend sem.  Quisque porta. Nulla pulvinar eleifend sem.Senznam uvnitř textuQuisque porta. Nulla pulvinar eleifend sem. Praesent id justo in neque elementumultrices. Aliquam erat volutpat. Etiam dictum tincidunt diam. Itaque earum rerumhic tenetur a sapiente delectus, ut aut reiciendis voluptatibus maiores aliasconsequatur aut perferendis doloribus asperiores repellat. Fusce tellus odio,dapibus id fermentum quis, suscipit id erat. Vestibulum erat nulla, ullamcorpernec, rutrum non, nonummy ac, erat. Nulla est. Donec iaculis gravida nulla.  Quisque porta. Nulla pulvinar eleifend sem.  Quisque porta. Nulla pulvinar eleifend sem.  Quisque porta. Nulla pulvinar eleifend sem.  Quisque porta. Nulla pulvinar eleifend sem.Vivamus porttitor turpis ac leo. Aliquam ante. Nullam justo enim, consectetuernec, ullamcorper ac, vestibulum in, elit. Maecenas libero. Aliquam ornare wisieu metus. Lorem ipsum dolor sit amet, consectetuer adipiscing elit. Duisbibendum, lectus ut viverra rhoncus, dolor nunc faucibus libero, eget facilisisenim ipsum id lacus. Nunc auctor. Fusce dui leo, imperdiet in, aliquam sit amet,feugiat eu, orci. Vestibulum fermentum tortor id mi. In dapibus augue nonsapien. Mauris elementum mauris vitae tortor.TabulkaVivamus luctus egestas leo.Maecenas ipsum velit, consectetuer eu lobortis ut, dictum at dui. Mauris dictumfacilisis augue. Aenean placerat. Nullam lectus justo, vulputate eget mollissed, tempor sed magna. Nullam feugiat, turpis at pulvinar vulputate, erat liberotristique tellus, nec bibendum odio risus sit amet ante. Fusce wisi. Phasellusenim erat, vestibulum vel, aliquam a, posuere eu, velit.      Vivamus porttitor turpis ac leo.    Integer vulputate sem a nibh rutrum consequat.    Integer tempor.        Vivamus porttitor turpis ac leo.    Integer vulputate sem a nibh rutrum consequat.    Integer tempor.        Vivamus porttitor turpis ac leo.    Integer vulputate sem a nibh rutrum consequat.    Integer tempor.        Vivamus porttitor turpis ac leo.    Integer vulputate sem a nibh rutrum consequat.    Integer tempor.  Cras elementum. Integer vulputate sem a nibh rutrum consequat. Integer tempor.Donec iaculis gravida nulla. Donec quis nibh at felis congue commodo. Vivamusporttitor turpis ac leo. Vivamus luctus egestas leo. Donec ipsum massa,ullamcorper in, auctor et, scelerisque sed, est. Phasellus rhoncus. Nam sedtellus id magna elementum tincidunt. Neque porro quisquam est, qui dolorem ipsumquia dolor sit amet, consectetur, adipisci velit, sed quia non numquam eius moditempora incidunt ut labore et dolore magnam aliquam quaerat voluptatem. Duisante orci, molestie vitae vehicula venenatis, tincidunt ac pede.",
      "url"      : "/aktuality/clanek-s-videem-misto-obrazku.html",
      "date"     : "2018-06-11 00:00:00 +0200"
    },
  
    {
      "title"    : "Článek s vložený videem uvnitř textu",
      "author"   : "Jmeno Prijmeni",
      "category" : "blog",
      "content"	 : "Posty musí být každý ve vlastním souboru pojmenovaném datumem a nejakym nazvem, například _posts/2018-03-14-slavime-pi-day.md. Tento název se pak objeví v adrese, tedy xxx.pirati.cz/aktuality/slavime-pi-day.html.Obrázky dávejte do assets/img/posts/Struktura  texty pište v Markdown  viz wikipediaYoutubeLze embeddovat pomocí vložení:{% include youtube.html id=&#39;id youtube videa&#39; %}Výsledek pak vypadá takto:Ukázky typografieNadpis 1Nadpis 2Nadpis 3Nadpis 4Nullam lectus justo, vulputate eget mollis sed, tempor sed magna. Etiam commododui eget wisi. Cras elementum. Etiam dictum tincidunt diam. Aliquam eratvolutpat. Duis sapien nunc, commodo et, interdum suscipit, sollicitudin et,dolor. Aliquam erat volutpat. Etiam ligula pede, sagittis quis, interdumultricies, scelerisque eu. Cras elementum. Vestibulum fermentum tortor id mi.Etiam quis quam. Mauris elementum mauris vitae tortor. Fusce tellus. Integerrutrum, orci vestibulum ullamcorper ultricies, lacus quam ultricies odio, vitaeplacerat pede sem sit amet enim. Ut enim ad minima veniam, quis nostrumexercitationem ullam corporis suscipit laboriosam, nisi ut aliquid ex ea commodiconsequatur?Nadpis 1Nullam lectus justo, vulputate eget mollis sed, tempor sed magna. Etiam commododui eget wisi. Cras elementum. Etiam dictum tincidunt diam. Aliquam eratvolutpat. Duis sapien nunc, commodo et, interdum suscipit, sollicitudin et,dolor. Aliquam erat volutpat.Nadpis 2Nullam lectus justo, vulputate eget mollis sed, tempor sed magna. Etiam commododui eget wisi. Cras elementum. Etiam dictum tincidunt diam. Aliquam eratvolutpat. Duis sapien nunc, commodo et, interdum suscipit, sollicitudin et,dolor. Aliquam erat volutpat.Nadpis 3Nullam lectus justo, vulputate eget mollis sed, tempor sed magna. Etiam commododui eget wisi. Cras elementum. Etiam dictum tincidunt diam. Aliquam eratvolutpat. Duis sapien nunc, commodo et, interdum suscipit, sollicitudin et,dolor. Aliquam erat volutpat.Nadpis 4Nullam lectus justo, vulputate eget mollis sed, tempor sed magna. Etiam commododui eget wisi. Cras elementum. Etiam dictum tincidunt diam. Aliquam eratvolutpat. Duis sapien nunc, commodo et, interdum suscipit, sollicitudin et,dolor. Aliquam erat volutpat.Nečíslovaný seznam  Quisque porta. Nulla pulvinar eleifend sem.  Quisque porta. Nulla pulvinar eleifend sem.  Quisque porta. Nulla pulvinar eleifend sem.  Quisque porta. Nulla pulvinar eleifend sem.Číslovaný seznam  Quisque porta. Nulla pulvinar eleifend sem.  Quisque porta. Nulla pulvinar eleifend sem.  Quisque porta. Nulla pulvinar eleifend sem.  Quisque porta. Nulla pulvinar eleifend sem.Senznam uvnitř textuQuisque porta. Nulla pulvinar eleifend sem. Praesent id justo in neque elementumultrices. Aliquam erat volutpat. Etiam dictum tincidunt diam. Itaque earum rerumhic tenetur a sapiente delectus, ut aut reiciendis voluptatibus maiores aliasconsequatur aut perferendis doloribus asperiores repellat. Fusce tellus odio,dapibus id fermentum quis, suscipit id erat. Vestibulum erat nulla, ullamcorpernec, rutrum non, nonummy ac, erat. Nulla est. Donec iaculis gravida nulla.  Quisque porta. Nulla pulvinar eleifend sem.  Quisque porta. Nulla pulvinar eleifend sem.  Quisque porta. Nulla pulvinar eleifend sem.  Quisque porta. Nulla pulvinar eleifend sem.Vivamus porttitor turpis ac leo. Aliquam ante. Nullam justo enim, consectetuernec, ullamcorper ac, vestibulum in, elit. Maecenas libero. Aliquam ornare wisieu metus. Lorem ipsum dolor sit amet, consectetuer adipiscing elit. Duisbibendum, lectus ut viverra rhoncus, dolor nunc faucibus libero, eget facilisisenim ipsum id lacus. Nunc auctor. Fusce dui leo, imperdiet in, aliquam sit amet,feugiat eu, orci. Vestibulum fermentum tortor id mi. In dapibus augue nonsapien. Mauris elementum mauris vitae tortor.TabulkaVivamus luctus egestas leo.Maecenas ipsum velit, consectetuer eu lobortis ut, dictum at dui. Mauris dictumfacilisis augue. Aenean placerat. Nullam lectus justo, vulputate eget mollissed, tempor sed magna. Nullam feugiat, turpis at pulvinar vulputate, erat liberotristique tellus, nec bibendum odio risus sit amet ante. Fusce wisi. Phasellusenim erat, vestibulum vel, aliquam a, posuere eu, velit.      Vivamus porttitor turpis ac leo.    Integer vulputate sem a nibh rutrum consequat.    Integer tempor.        Vivamus porttitor turpis ac leo.    Integer vulputate sem a nibh rutrum consequat.    Integer tempor.        Vivamus porttitor turpis ac leo.    Integer vulputate sem a nibh rutrum consequat.    Integer tempor.        Vivamus porttitor turpis ac leo.    Integer vulputate sem a nibh rutrum consequat.    Integer tempor.  Cras elementum. Integer vulputate sem a nibh rutrum consequat. Integer tempor.Donec iaculis gravida nulla. Donec quis nibh at felis congue commodo. Vivamusporttitor turpis ac leo. Vivamus luctus egestas leo. Donec ipsum massa,ullamcorper in, auctor et, scelerisque sed, est. Phasellus rhoncus. Nam sedtellus id magna elementum tincidunt. Neque porro quisquam est, qui dolorem ipsumquia dolor sit amet, consectetur, adipisci velit, sed quia non numquam eius moditempora incidunt ut labore et dolore magnam aliquam quaerat voluptatem. Duisante orci, molestie vitae vehicula venenatis, tincidunt ac pede.",
      "url"      : "/aktuality/clanek-s-embednutym-videem.html",
      "date"     : "2018-06-10 00:00:00 +0200"
    },
  
    {
      "title"    : "Nadpis článku",
      "author"   : "Jmeno Prijmeni",
      "category" : "blog",
      "content"	 : "Posty musí být každý ve vlastním souboru pojmenovaném datumem a nejakym nazvem, například _posts/2018-03-14-slavime-pi-day.md. Tento název se pak objeví v adrese, tedy xxx.pirati.cz/aktuality/slavime-pi-day.html.Obrázky dávejte do assets/img/posts/Struktura  texty pište v Markdown  viz wikipediaUkázky typografieNadpis 1Nadpis 2Nadpis 3Nadpis 4Nullam lectus justo, vulputate eget mollis sed, tempor sed magna. Etiam commododui eget wisi. Cras elementum. Etiam dictum tincidunt diam. Aliquam eratvolutpat. Duis sapien nunc, commodo et, interdum suscipit, sollicitudin et,dolor. Aliquam erat volutpat. Etiam ligula pede, sagittis quis, interdumultricies, scelerisque eu. Cras elementum. Vestibulum fermentum tortor id mi.Etiam quis quam. Mauris elementum mauris vitae tortor. Fusce tellus. Integerrutrum, orci vestibulum ullamcorper ultricies, lacus quam ultricies odio, vitaeplacerat pede sem sit amet enim. Ut enim ad minima veniam, quis nostrumexercitationem ullam corporis suscipit laboriosam, nisi ut aliquid ex ea commodiconsequatur?Nadpis 1Nullam lectus justo, vulputate eget mollis sed, tempor sed magna. Etiam commododui eget wisi. Cras elementum. Etiam dictum tincidunt diam. Aliquam eratvolutpat. Duis sapien nunc, commodo et, interdum suscipit, sollicitudin et,dolor. Aliquam erat volutpat.Nadpis 2Nullam lectus justo, vulputate eget mollis sed, tempor sed magna. Etiam commododui eget wisi. Cras elementum. Etiam dictum tincidunt diam. Aliquam eratvolutpat. Duis sapien nunc, commodo et, interdum suscipit, sollicitudin et,dolor. Aliquam erat volutpat.Nadpis 3Nullam lectus justo, vulputate eget mollis sed, tempor sed magna. Etiam commododui eget wisi. Cras elementum. Etiam dictum tincidunt diam. Aliquam eratvolutpat. Duis sapien nunc, commodo et, interdum suscipit, sollicitudin et,dolor. Aliquam erat volutpat.Nadpis 4Nullam lectus justo, vulputate eget mollis sed, tempor sed magna. Etiam commododui eget wisi. Cras elementum. Etiam dictum tincidunt diam. Aliquam eratvolutpat. Duis sapien nunc, commodo et, interdum suscipit, sollicitudin et,dolor. Aliquam erat volutpat.Nečíslovaný seznam  Quisque porta. Nulla pulvinar eleifend sem.  Quisque porta. Nulla pulvinar eleifend sem.  Quisque porta. Nulla pulvinar eleifend sem.  Quisque porta. Nulla pulvinar eleifend sem.Číslovaný seznam  Quisque porta. Nulla pulvinar eleifend sem.  Quisque porta. Nulla pulvinar eleifend sem.  Quisque porta. Nulla pulvinar eleifend sem.  Quisque porta. Nulla pulvinar eleifend sem.Senznam uvnitř textuQuisque porta. Nulla pulvinar eleifend sem. Praesent id justo in neque elementumultrices. Aliquam erat volutpat. Etiam dictum tincidunt diam. Itaque earum rerumhic tenetur a sapiente delectus, ut aut reiciendis voluptatibus maiores aliasconsequatur aut perferendis doloribus asperiores repellat. Fusce tellus odio,dapibus id fermentum quis, suscipit id erat. Vestibulum erat nulla, ullamcorpernec, rutrum non, nonummy ac, erat. Nulla est. Donec iaculis gravida nulla.  Quisque porta. Nulla pulvinar eleifend sem.  Quisque porta. Nulla pulvinar eleifend sem.  Quisque porta. Nulla pulvinar eleifend sem.  Quisque porta. Nulla pulvinar eleifend sem.Vivamus porttitor turpis ac leo. Aliquam ante. Nullam justo enim, consectetuernec, ullamcorper ac, vestibulum in, elit. Maecenas libero. Aliquam ornare wisieu metus. Lorem ipsum dolor sit amet, consectetuer adipiscing elit. Duisbibendum, lectus ut viverra rhoncus, dolor nunc faucibus libero, eget facilisisenim ipsum id lacus. Nunc auctor. Fusce dui leo, imperdiet in, aliquam sit amet,feugiat eu, orci. Vestibulum fermentum tortor id mi. In dapibus augue nonsapien. Mauris elementum mauris vitae tortor.TabulkaVivamus luctus egestas leo.Maecenas ipsum velit, consectetuer eu lobortis ut, dictum at dui. Mauris dictumfacilisis augue. Aenean placerat. Nullam lectus justo, vulputate eget mollissed, tempor sed magna. Nullam feugiat, turpis at pulvinar vulputate, erat liberotristique tellus, nec bibendum odio risus sit amet ante. Fusce wisi. Phasellusenim erat, vestibulum vel, aliquam a, posuere eu, velit.      Vivamus porttitor turpis ac leo.    Integer vulputate sem a nibh rutrum consequat.    Integer tempor.        Vivamus porttitor turpis ac leo.    Integer vulputate sem a nibh rutrum consequat.    Integer tempor.        Vivamus porttitor turpis ac leo.    Integer vulputate sem a nibh rutrum consequat.    Integer tempor.        Vivamus porttitor turpis ac leo.    Integer vulputate sem a nibh rutrum consequat.    Integer tempor.  Cras elementum. Integer vulputate sem a nibh rutrum consequat. Integer tempor.Donec iaculis gravida nulla. Donec quis nibh at felis congue commodo. Vivamusporttitor turpis ac leo. Vivamus luctus egestas leo. Donec ipsum massa,ullamcorper in, auctor et, scelerisque sed, est. Phasellus rhoncus. Nam sedtellus id magna elementum tincidunt. Neque porro quisquam est, qui dolorem ipsumquia dolor sit amet, consectetur, adipisci velit, sed quia non numquam eius moditempora incidunt ut labore et dolore magnam aliquam quaerat voluptatem. Duisante orci, molestie vitae vehicula venenatis, tincidunt ac pede.",
      "url"      : "/aktuality/priklad.html",
      "date"     : "2018-03-14 00:00:00 +0100"
    }
  
]
